x4xl/__init__.py
x4xl/x4xl.py
x4xl-0.0.2.dist-info/METADATA
x4xl-0.0.2.dist-info/WHEEL
x4xl-0.0.2.dist-info/licenses/LICENCE
x4xl-0.0.2.dist-info/RECORD
